se_exporter/__init__.py
se_exporter/__version__.py
se_exporter/main.py
se_exporter/client/__init__.py
se_exporter/client/prometheus.py
se_exporter/client/vrage.py
se_exporter/models/__init__.py
se_exporter/models/base.py
se_exporter/utils/__init__.py
se_exporter/utils/config.py
se_exporter/utils/helpers.py
se_exporter-1.0.2.dist-info/LICENSE
se_exporter-1.0.2.dist-info/METADATA
se_exporter-1.0.2.dist-info/WHEEL
se_exporter-1.0.2.dist-info/entry_points.txt
se_exporter-1.0.2.dist-info/top_level.txt
se_exporter-1.0.2.dist-info/RECORD
