Metadata-Version: 2.1
Name: se-exporter
Version: 1.0.2
Summary: Prometheus exporter for Space Engineer Server
Home-page: https://github.com/akimrx/space-engineers-exporter
Author: Akim Faskhutdinov
Author-email: akimstrong@yandex.ru
License: MIT
Keywords: space engineers exporter,prometheus,space engineers server
Platform: osx
Platform: linux
Classifier: Programming Language :: Python :: 3.6
Classifier: Programming Language :: Python :: 3.7
Classifier: Programming Language :: Python :: 3.8
Classifier: Programming Language :: Python :: 3.9
Classifier: License :: OSI Approved :: MIT License
Classifier: Operating System :: OS Independent
Classifier: Intended Audience :: Developers
Classifier: Intended Audience :: System Administrators
Classifier: Topic :: System :: Monitoring
Requires-Python: >=3.6
Requires-Dist: pyyaml (==5.3.1)
Requires-Dist: chardet (==3.0.4)
Requires-Dist: requests (==2.25.1)
Requires-Dist: aiohttp (==3.7.3)
Requires-Dist: prometheus-client (==0.9.0)
